QIP-0.4.0.dist-info/METADATA
QIP-0.4.0.dist-info/RECORD
QIP-0.4.0.dist-info/WHEEL
QIP-0.4.0.dist-info/top_level.txt
qip/__init__.py
qip/backend.py
qip/operators.py
qip/pipeline.py
qip/qfft.py
qip/qip.py
qip/qubit_util.py
qip/svgwriter.py
qip/util.py
qip/ext/__init__.py
qip/ext/func_apply.cpython-36m-darwin.so
qip/ext/kronprod.cpython-36m-darwin.so
qip/ext/util.cpython-36m-darwin.so
